COPYING
MANIFEST.in
README
setup.py
examples/.DS_Store
examples/ijrr2013/ijrr2013.py
examples/ijrr2013/robot_1.txt
examples/ijrr2013/robot_2.txt
examples/ijrr2014_inc_syn/ijrr2014_inc_syn.py
examples/ijrr2014_inc_syn/target_1.txt
examples/ijrr2014_inc_syn/target_2.txt
examples/ijrr2014_inc_syn/target_3.txt
examples/ijrr2014_inc_syn/target_4.txt
examples/ijrr2014_inc_syn/target_5.txt
examples/ijrr2014_inc_syn/trap_1.txt
examples/ijrr2014_inc_syn/trap_2.txt
examples/ijrr2014_inc_syn/trap_3.txt
examples/ijrr2014_inc_syn/trap_4.txt
examples/ijrr2014_inc_syn/trap_5.txt
examples/ijrr2014_inc_syn/trap_6.txt
examples/ijrr2014_inc_syn/vehicle_1.txt
examples/ijrr2014_inc_syn/vehicle_2.txt
examples/ijrr2014_rec_hor/environment.py
examples/ijrr2014_rec_hor/environment.pyc
examples/ijrr2014_rec_hor/main.py
examples/ijrr2014_rec_hor/planner.py
examples/ijrr2014_rec_hor/planner.pyc
examples/ijrr2014_rec_hor/quadrotor.py
examples/ijrr2014_rec_hor/quadrotor.pyc
examples/ijrr2014_rec_hor/view.py
examples/ijrr2014_rec_hor/view.pyc
lomap/COPYING
lomap/README
lomap/__init__.py
lomap.egg-info/PKG-INFO
lomap.egg-info/SOURCES.txt
lomap.egg-info/dependency_links.txt
lomap.egg-info/requires.txt
lomap.egg-info/top_level.txt
lomap/algorithms/__init__.py
lomap/algorithms/dijkstra.py
lomap/algorithms/field_event_ts.py
lomap/algorithms/graph_search.py
lomap/algorithms/inc_syn.py
lomap/algorithms/multi_agent_optimal_run.py
lomap/algorithms/optimal_run.py
lomap/algorithms/product.py
lomap/algorithms/robust_multi_agent_optimal_run.py
lomap/algorithms/sync_seq.py
lomap/algorithms/value_iteration.py
lomap/binaries/linux/ltl2ba
lomap/binaries/linux/scheck2
lomap/binaries/mac/ltl2ba
lomap/binaries/mac/scheck2
lomap/classes/__init__.py
lomap/classes/buchi.py
lomap/classes/fsa.py
lomap/classes/interval.py
lomap/classes/markov.py
lomap/classes/model.py
lomap/classes/timer.py
lomap/classes/ts.py
lomap/examples/ijrr2013/ijrr2013.py
lomap/examples/ijrr2013/robot_1.txt
lomap/examples/ijrr2013/robot_2.txt
lomap/examples/ijrr2014_inc_syn/ijrr2014_inc_syn.py
lomap/examples/ijrr2014_inc_syn/target_1.txt
lomap/examples/ijrr2014_inc_syn/target_2.txt
