Metadata-Version: 1.0
Name: lomap
Version: 0.1.1.post1
Summary: LTL Optimal Multi-Agent Planner (LOMAP)
Home-page: http://hyness.bu.edu/lomap
Author: Alphan Ulusoy
Author-email: alphan@bu.edu
License: GNU GPL
Platform: UNKNOWN
